Classfile /home/mayuresh/workspace/github/java-code-samples/target/classes/nl/cmyrsh/methods/UsingFunction.class
  Last modified Jun 19, 2022; size 1688 bytes
  SHA-256 checksum 8be7f25a0764dbe785cb8a6bc4053064cb73d75a21f83dbd90cd3afb71f4b2e9
  Compiled from "UsingFunction.java"
public class nl.cmyrsh.methods.UsingFunction
  minor version: 0
  major version: 55
  flags: (0x0021) ACC_PUBLIC, ACC_SUPER
  this_class: #16                         // nl/cmyrsh/methods/UsingFunction
  super_class: #2                         // java/lang/Object
  interfaces: 0, fields: 1, methods: 3, attributes: 3
Constant pool:
   #1 = Methodref          #2.#3          // java/lang/Object."<init>":()V
   #2 = Class              #4             // java/lang/Object
   #3 = NameAndType        #5:#6          // "<init>":()V
   #4 = Utf8               java/lang/Object
   #5 = Utf8               <init>
   #6 = Utf8               ()V
   #7 = String             #8             // Hello World
   #8 = Utf8               Hello World
   #9 = Fieldref           #10.#11        // java/lang/System.out:Ljava/io/PrintStream;
  #10 = Class              #12            // java/lang/System
  #11 = NameAndType        #13:#14        // out:Ljava/io/PrintStream;
  #12 = Utf8               java/lang/System
  #13 = Utf8               out
  #14 = Utf8               Ljava/io/PrintStream;
  #15 = Fieldref           #16.#17        // nl/cmyrsh/methods/UsingFunction.operate:Ljava/util/function/Function;
  #16 = Class              #18            // nl/cmyrsh/methods/UsingFunction
  #17 = NameAndType        #19:#20        // operate:Ljava/util/function/Function;
  #18 = Utf8               nl/cmyrsh/methods/UsingFunction
  #19 = Utf8               operate
  #20 = Utf8               Ljava/util/function/Function;
  #21 = InterfaceMethodref #22.#23        // java/util/function/Function.apply:(Ljava/lang/Object;)Ljava/lang/Object;
  #22 = Class              #24            // java/util/function/Function
  #23 = NameAndType        #25:#26        // apply:(Ljava/lang/Object;)Ljava/lang/Object;
  #24 = Utf8               java/util/function/Function
  #25 = Utf8               apply
  #26 = Utf8               (Ljava/lang/Object;)Ljava/lang/Object;
  #27 = Class              #28            // java/lang/String
  #28 = Utf8               java/lang/String
  #29 = Methodref          #30.#31        // java/io/PrintStream.println:(Ljava/lang/String;)V
  #30 = Class              #32            // java/io/PrintStream
  #31 = NameAndType        #33:#34        // println:(Ljava/lang/String;)V
  #32 = Utf8               java/io/PrintStream
  #33 = Utf8               println
  #34 = Utf8               (Ljava/lang/String;)V
  #35 = Methodref          #36.#37        // java/util/UUID.randomUUID:()Ljava/util/UUID;
  #36 = Class              #38            // java/util/UUID
  #37 = NameAndType        #39:#40        // randomUUID:()Ljava/util/UUID;
  #38 = Utf8               java/util/UUID
  #39 = Utf8               randomUUID
  #40 = Utf8               ()Ljava/util/UUID;
  #41 = Methodref          #36.#42        // java/util/UUID.toString:()Ljava/lang/String;
  #42 = NameAndType        #43:#44        // toString:()Ljava/lang/String;
  #43 = Utf8               toString
  #44 = Utf8               ()Ljava/lang/String;
  #45 = Methodref          #46.#47        // java/util/Objects.requireNonNull:(Ljava/lang/Object;)Ljava/lang/Object;
  #46 = Class              #48            // java/util/Objects
  #47 = NameAndType        #49:#26        // requireNonNull:(Ljava/lang/Object;)Ljava/lang/Object;
  #48 = Utf8               java/util/Objects
  #49 = Utf8               requireNonNull
  #50 = InvokeDynamic      #0:#51         // #0:apply:(Ljava/lang/String;)Ljava/util/function/Function;
  #51 = NameAndType        #25:#52        // apply:(Ljava/lang/String;)Ljava/util/function/Function;
  #52 = Utf8               (Ljava/lang/String;)Ljava/util/function/Function;
  #53 = Utf8               Signature
  #54 = Utf8               Ljava/util/function/Function<Ljava/lang/String;Ljava/lang/String;>;
  #55 = Utf8               Code
  #56 = Utf8               LineNumberTable
  #57 = Utf8               LocalVariableTable
  #58 = Utf8               this
  #59 = Utf8               Lnl/cmyrsh/methods/UsingFunction;
  #60 = Utf8               main
  #61 = Utf8               ([Ljava/lang/String;)V
  #62 = Utf8               args
  #63 = Utf8               [Ljava/lang/String;
  #64 = Utf8               hello
  #65 = Utf8               Ljava/lang/String;
  #66 = Utf8               <clinit>
  #67 = Utf8               SourceFile
  #68 = Utf8               UsingFunction.java
  #69 = Utf8               BootstrapMethods
  #70 = MethodHandle       6:#71          // REF_invokeStatic java/lang/invoke/LambdaMetafactory.metafactory:(Ljava/lang/invoke/MethodHandles$Lookup;Ljava/lang/String;Ljava/lang/invoke/MethodType;Ljava/lang/invoke/MethodType;Ljava/lang/invoke/MethodHandle;Ljava/lang/invoke/MethodType;)Ljava/lang/invoke/CallSite;
  #71 = Methodref          #72.#73        // java/lang/invoke/LambdaMetafactory.metafactory:(Ljava/lang/invoke/MethodHandles$Lookup;Ljava/lang/String;Ljava/lang/invoke/MethodType;Ljava/lang/invoke/MethodType;Ljava/lang/invoke/MethodHandle;Ljava/lang/invoke/MethodType;)Ljava/lang/invoke/CallSite;
  #72 = Class              #74            // java/lang/invoke/LambdaMetafactory
  #73 = NameAndType        #75:#76        // metafactory:(Ljava/lang/invoke/MethodHandles$Lookup;Ljava/lang/String;Ljava/lang/invoke/MethodType;Ljava/lang/invoke/MethodType;Ljava/lang/invoke/MethodHandle;Ljava/lang/invoke/MethodType;)Ljava/lang/invoke/CallSite;
  #74 = Utf8               java/lang/invoke/LambdaMetafactory
  #75 = Utf8               metafactory
  #76 = Utf8               (Ljava/lang/invoke/MethodHandles$Lookup;Ljava/lang/String;Ljava/lang/invoke/MethodType;Ljava/lang/invoke/MethodType;Ljava/lang/invoke/MethodHandle;Ljava/lang/invoke/MethodType;)Ljava/lang/invoke/CallSite;
  #77 = MethodType         #26            //  (Ljava/lang/Object;)Ljava/lang/Object;
  #78 = MethodHandle       5:#79          // REF_invokeVirtual java/lang/String.concat:(Ljava/lang/String;)Ljava/lang/String;
  #79 = Methodref          #27.#80        // java/lang/String.concat:(Ljava/lang/String;)Ljava/lang/String;
  #80 = NameAndType        #81:#82        // concat:(Ljava/lang/String;)Ljava/lang/String;
  #81 = Utf8               concat
  #82 = Utf8               (Ljava/lang/String;)Ljava/lang/String;
  #83 = MethodType         #82            //  (Ljava/lang/String;)Ljava/lang/String;
  #84 = Utf8               InnerClasses
  #85 = Class              #86            // java/lang/invoke/MethodHandles$Lookup
  #86 = Utf8               java/lang/invoke/MethodHandles$Lookup
  #87 = Class              #88            // java/lang/invoke/MethodHandles
  #88 = Utf8               java/lang/invoke/MethodHandles
  #89 = Utf8               Lookup
{
  private static java.util.function.Function<java.lang.String, java.lang.String> operate;
    descriptor: Ljava/util/function/Function;
    flags: (0x000a) ACC_PRIVATE, ACC_STATIC
    Signature: #54                          // Ljava/util/function/Function<Ljava/lang/String;Ljava/lang/String;>;

  public nl.cmyrsh.methods.UsingFunction();
    descriptor: ()V
    flags: (0x0001) ACC_PUBLIC
    Code:
      stack=1, locals=1, args_size=1
         0: aload_0
         1: invokespecial #1                  // Method java/lang/Object."<init>":()V
         4: return
      LineNumberTable:
        line 6: 0
      LocalVariableTable:
        Start  Length  Slot  Name   Signature
            0       5     0  this   Lnl/cmyrsh/methods/UsingFunction;

  public static void main(java.lang.String[]);
    descriptor: ([Ljava/lang/String;)V
    flags: (0x0009) ACC_PUBLIC, ACC_STATIC
    Code:
      stack=3, locals=2, args_size=1
         0: ldc           #7                  // String Hello World
         2: astore_1
         3: getstatic     #9                  // Field java/lang/System.out:Ljava/io/PrintStream;
         6: getstatic     #15                 // Field operate:Ljava/util/function/Function;
         9: aload_1
        10: invokeinterface #21,  2           // InterfaceMethod java/util/function/Function.apply:(Ljava/lang/Object;)Ljava/lang/Object;
        15: checkcast     #27                 // class java/lang/String
        18: invokevirtual #29                 // Method java/io/PrintStream.println:(Ljava/lang/String;)V
        21: return
      LineNumberTable:
        line 13: 0
        line 14: 3
        line 15: 21
      LocalVariableTable:
        Start  Length  Slot  Name   Signature
            0      22     0  args   [Ljava/lang/String;
            3      19     1 hello   Ljava/lang/String;

  static {};
    descriptor: ()V
    flags: (0x0008) ACC_STATIC
    Code:
      stack=2, locals=0, args_size=0
         0: invokestatic  #35                 // Method java/util/UUID.randomUUID:()Ljava/util/UUID;
         3: invokevirtual #41                 // Method java/util/UUID.toString:()Ljava/lang/String;
         6: dup
         7: invokestatic  #45                 // Method java/util/Objects.requireNonNull:(Ljava/lang/Object;)Ljava/lang/Object;
        10: pop
        11: invokedynamic #50,  0             // InvokeDynamic #0:apply:(Ljava/lang/String;)Ljava/util/function/Function;
        16: putstatic     #15                 // Field operate:Ljava/util/function/Function;
        19: return
      LineNumberTable:
        line 10: 0
}
SourceFile: "UsingFunction.java"
BootstrapMethods:
  0: #70 REF_invokeStatic java/lang/invoke/LambdaMetafactory.metafactory:(Ljava/lang/invoke/MethodHandles$Lookup;Ljava/lang/String;Ljava/lang/invoke/MethodType;Ljava/lang/invoke/MethodType;Ljava/lang/invoke/MethodHandle;Ljava/lang/invoke/MethodType;)Ljava/lang/invoke/CallSite;
    Method arguments:
      #77 (Ljava/lang/Object;)Ljava/lang/Object;
      #78 REF_invokeVirtual java/lang/String.concat:(Ljava/lang/String;)Ljava/lang/String;
      #83 (Ljava/lang/String;)Ljava/lang/String;
InnerClasses:
  public static final #89= #85 of #87;    // Lookup=class java/lang/invoke/MethodHandles$Lookup of class java/lang/invoke/MethodHandles
